{
  "project_info": {
    "project_number": "701236401251",
    "firebase_url": "https://jourtrip-2cee5.firebaseio.com",
    "project_id": "jourtrip-2cee5",
    "storage_bucket": "jourtrip-2cee5.appspot.com"
  },
  "client": [
    {
      "client_info": {
        "mobilesdk_app_id": "1:701236401251:android:d94424af22b66c7c",
        "android_client_info": {
          "package_name": "com.zigerianos.jourtrip"
        }
      },
      "oauth_client": [
        {
          "client_id": "701236401251-2o697k5rp629ssccm1u6vri4sckbh40l.apps.googleusercontent.com",
          "client_type": 3
        }
      ],
      "api_key": [
        {
          "current_key": "AIzaSyDc9ILpfrPG1j1Pbcq7AIfi-qtTPpjqw20"
        }
      ],
      "services": {
        "appinvite_service": {
          "other_platform_oauth_client": [
            {
              "client_id": "701236401251-2o697k5rp629ssccm1u6vri4sckbh40l.apps.googleusercontent.com",
              "client_type": 3
            }
          ]
        }
      }
    }
  ],
  "configuration_version": "1"
}